{
  "id": "ckzi38wix0218e2n09ncgnmxx",
  "name": "Interagir",
  "subtitle": "Prendre soin des autres et du monde",
  "skills": [
    "ckzi3e4as1251e2n0fz614xn4",
    "ckzi3ef9s1366e2n082dhihsm",
    "ckzi3eor91487e2n0qdoa639u",
    "ckzi3ezut1614e2n07fab18pt"
  ],
  "description": "Le fait de respecter les autres, d’en prendre soin et de se sentir connecté à eux – nos voisins, les générations futures, ou la biosphère, par exemple – nous aide à créer des systèmes et des sociétés plus justes et durables pour tout le monde."
}